decode_mcd/__init__.py
decode_mcd/counterfactuals_generator.py
decode_mcd/data_package.py
decode_mcd/design_targets.py
decode_mcd/mcd_exceptions.py
decode_mcd/multi_objective_problem.py
decode_mcd_private/DPPsampling.py
decode_mcd_private/__init__.py
decode_mcd_private/calculate_dtai.py
decode_mcd_private/classification_evaluator.py
decode_mcd_private/efficient_mixed_duplicate_elimination.py
decode_mcd_private/stats_methods.py
decode_mcd_private/validation_utils.py
decode_mcd-2024.2.20.dist-info/LICENSE
decode_mcd-2024.2.20.dist-info/METADATA
decode_mcd-2024.2.20.dist-info/WHEEL
decode_mcd-2024.2.20.dist-info/top_level.txt
decode_mcd-2024.2.20.dist-info/RECORD
