Metadata-Version: 2.1
Name: decode-mcd
Version: 2024.2.20
Summary: MCD generates counterfactuals that meet multiple, customizable objectives in both the feature and performance spaces.
Author: Lyle Regenwetter & Yazan Abu Obaideh
License: MIT License
Project-URL: Homepage, https://github.com/Lyleregenwetter/Multiobjective-Counterfactuals-for-Design
Keywords: counterfactuals,design,multi-objective,multiobjective,machine-learning
Classifier: License :: OSI Approved :: MIT License
Classifier: Programming Language :: Python
Classifier: Programming Language :: Python :: 3
Requires-Python: >=3.8
License-File: LICENSE
Requires-Dist: numpy >=1.26.0
Requires-Dist: pandas
Requires-Dist: pymoo
Requires-Dist: dill
